deliveryboy/__init__.py
deliveryboy/__main__.py
deliveryboy/core.py
deliveryboy/exceptions.py
deliveryboy/pickle.py
deliveryboy/tests/__init__.py
deliveryboy/tests/base.py
deliveryboy/tests/tests.py
deliveryboy-0.1.0.dist-info/METADATA
deliveryboy-0.1.0.dist-info/RECORD
deliveryboy-0.1.0.dist-info/WHEEL
deliveryboy-0.1.0.dist-info/top_level.txt
