Metadata-Version: 2.1
Name: deliveryboy
Version: 0.1.0
Summary: UNKNOWN
Home-page: UNKNOWN
Author: Andreas Hasenkopf
Author-email: andi@hasenkopf2000.net
Maintainer: Andreas Hasenkopf
Maintainer-email: andi@hasenkopf2000.net
License: MIT
Project-URL: Documentation, https://readthedocs.org/projects/deliveryboy/
Project-URL: Source Code, https://github.com/crazyscientist/deliveryboy
Project-URL: Bug Tracker, https://github.com/crazyscientist/deliveryboy/issues
Keywords: sudo ssh
Platform: UNKNOWN
Classifier: Development Status :: 3 - Alpha
Classifier: Intended Audience :: Developers
Classifier: Intended Audience :: System Administrators
Classifier: License :: OSI Approved :: MIT License
Classifier: Operating System :: POSIX :: Linux
Classifier: Programming Language :: Python :: 3 :: Only
Classifier: Topic :: System :: Distributed Computing
Requires-Dist: dill
